ccd_single.py
ccd_time.py
ccd_tools-0.8.17.data/scripts/ccd_list_ip.py
ccd_tools-0.8.17.data/scripts/dd_space_time.py
ccd_tools-0.8.17.data/scripts/dd_test.py
ccd_tools-0.8.17.data/scripts/ddplot.py
ccd_tools-0.8.17.data/scripts/ddps.py
ccd_tools-0.8.17.data/scripts/ddpst.py
ccd_tools-0.8.17.data/scripts/ddpt.py
lib_ccd_test/__init__.py
lib_ccd_test/run_test.py
lib_dd/Jacobian.py
lib_dd/__init__.py
lib_dd/base_class.py
lib_dd/int_pars.py
lib_dd/interface.py
lib_dd/plot.py
lib_dd/plot_stats.py
lib_dd/starting_parameters.py
lib_dd/test_functions.py
lib_dd/version.py
lib_dd/apps/__init__.py
lib_dd/apps/ccd_single.py
lib_dd/conductivity/__init__.py
lib_dd/conductivity/model.py
lib_dd/config/__init__.py
lib_dd/config/cfg_base.py
lib_dd/config/cfg_single.py
lib_dd/config/cfg_time.py
lib_dd/decomposition/__init__.py
lib_dd/decomposition/ccd_single.py
lib_dd/decomposition/ccd_single_stateless.py
lib_dd/io/__init__.py
lib_dd/io/ascii.py
lib_dd/io/ascii_audit.py
lib_dd/io/helper.py
lib_dd/io/io_general.py
lib_dd/models/__init__.py
lib_dd/models/ccd_cond.py
lib_dd/models/ccd_em_res.py
lib_dd/models/ccd_res.py
ccd_tools-0.8.17.dist-info/LICENCE
ccd_tools-0.8.17.dist-info/METADATA
ccd_tools-0.8.17.dist-info/WHEEL
ccd_tools-0.8.17.dist-info/entry_points.txt
ccd_tools-0.8.17.dist-info/top_level.txt
ccd_tools-0.8.17.dist-info/RECORD
