Metadata-Version: 2.1
Name: ccd-tools
Version: 0.8.17
Summary: Time-lapse Cole-Cole decomposition routines
Home-page: https://github.com/m-weigand/ccd_tools
Author: Maximilian Weigand and Department of Geophysics,University of Bonn, Germany
Author-email: mweigand@geo.uni-bonn.de
License: GPL-3
Keywords: SIP, Cole-Cole model,Debye decomposition,Cole-Cole decomposition
Platform: UNKNOWN
Classifier: Development Status :: 5 - Production/Stable
Classifier: License :: OSI Approved :: GNU Lesser General Public License v3 (LGPLv3)
Classifier: Programming Language :: Python :: 3.4
Classifier: Programming Language :: Python :: 3.5
Classifier: Programming Language :: Python :: 3.6
Classifier: Intended Audience :: Science/Research
Requires-Dist: numpy
Requires-Dist: scipy
Requires-Dist: matplotlib
Requires-Dist: geccoinv
Requires-Dist: sip-models
